camerahub/__init__.py
camerahub/middleware.py
camerahub/settings.py
camerahub/urls.py
camerahub/wsgi.py
schema/__init__.py
schema/admin.py
schema/apps.py
schema/filters.py
schema/fixtures/Condition.json
schema/fixtures/ExposureProgram.json
schema/fixtures/Filmstock.json
schema/fixtures/Format.json
schema/fixtures/Manufacturer.json
schema/fixtures/MeteringMode.json
schema/fixtures/MeteringType.json
schema/fixtures/Mount.json
schema/fixtures/NegativeSize.json
schema/fixtures/Process.json
schema/fixtures/ShutterSpeed.json
schema/formhelpers.py
schema/forms.py
schema/funcs.py
schema/management/commands/generate_icons.py
schema/migrations/0001_initial.py
schema/migrations/0002_data.py
schema/migrations/0003_shutter_speeds.py
schema/migrations/0004_manufacturers.py
schema/migrations/0005_formats.py
schema/migrations/0006_negative_sizes.py
schema/migrations/0007_mounts.py
schema/migrations/0008_filmstocks.py
schema/migrations/0009_auto_20191015_0926.py
schema/migrations/0010_auto_20191016_1023.py
schema/migrations/0011_auto_20191016_1035.py
schema/migrations/0012_auto_20191016_1106.py
schema/migrations/0013_delete_filteradapter.py
schema/migrations/0014_auto_20191031_1127.py
schema/migrations/0015_auto_20191107_1108.py
schema/migrations/0016_auto_20191107_2005.py
schema/migrations/0017_auto_20191108_1224.py
schema/migrations/0018_auto_20191217_2303.py
schema/migrations/0019_auto_20200110_1728_squashed_0020_auto_20200110_1734.py
schema/migrations/0020_create_superuser.py
schema/migrations/0021_auto_20200222_1856.py
schema/migrations/0022_auto_20200229_1954.py
schema/migrations/0023_auto_20200304_2020.py
schema/migrations/0024_cameramodel_shoe.py
schema/migrations/0025_convert_shoe_data.py
schema/migrations/0026_auto_20200305_1032.py
schema/migrations/0027_auto_20200306_2156.py
schema/migrations/0028_cameramodel_x_sync.py
schema/migrations/0029_remove_paperstock_tonable.py
schema/migrations/0030_auto_20200317_1344.py
schema/migrations/0031_auto_20200317_1404.py
camerahub-0.37.5.dist-info/METADATA
camerahub-0.37.5.dist-info/WHEEL
camerahub-0.37.5.dist-info/RECORD
