Metadata-Version: 2.1
Name: camerahub
Version: 0.37.5
Summary: App for cataloguing vintage cameras, lenses, films, negatives & prints
Home-page: https://camerahub.info/
License: Apache-2.0
Author: Jonathan Gazeley
Author-email: camerahub@jonathangazeley.com
Requires-Python: >=3.10,<4.0
Classifier: Development Status :: 4 - Beta
Classifier: Environment :: Web Environment
Classifier: Framework :: Django
Classifier: Framework :: Django :: 2.2
Classifier: Intended Audience :: End Users/Desktop
Classifier: License :: OSI Approved :: Apache Software License
Classifier: Natural Language :: English
Classifier: Operating System :: POSIX :: Linux
Classifier: Programming Language :: Python :: 3
Classifier: Programming Language :: Python :: 3.10
Classifier: Programming Language :: Python :: 3.11
Classifier: Programming Language :: Python :: 3.12
Classifier: Topic :: Database
Classifier: Topic :: Internet :: WWW/HTTP :: WSGI :: Application
Provides-Extra: pgsql
Requires-Dist: Django (>=3,<4)
Requires-Dist: awesome-slugify (>=1.6.5,<2.0.0)
Requires-Dist: django-autocomplete-light (>=3.9,<4.0)
Requires-Dist: django-autosequence (>=0,<1)
Requires-Dist: django-bootstrap-datepicker-plus (>=4,<5)
Requires-Dist: django-choices (>=1.7,<2.0)
Requires-Dist: django-colorfield (>=0.7,<0.8)
Requires-Dist: django-countries (>=7,<8)
Requires-Dist: django-crispy-forms (>=1.14,<2.0)
Requires-Dist: django-currentuser (>=0.5,<0.6)
Requires-Dist: django-dbbackup (>=3,<4)
Requires-Dist: django-filter
Requires-Dist: django-fullurl (>=1,<2)
Requires-Dist: django-geoposition-2 (>=0.3.11,<0.4.0)
Requires-Dist: django-health-check (>=3.17,<4.0)
Requires-Dist: django-leaflet (>=0.28,<0.29)
Requires-Dist: django-money (>=3,<4)
Requires-Dist: django-prometheus (>=2.2,<3.0)
Requires-Dist: django-registration (>=3.0,<4.0)
Requires-Dist: django-settings-export (>=1.2,<2.0)
Requires-Dist: django-simple-history (>=3,<4)
Requires-Dist: django-social-share (>=2,<3)
Requires-Dist: django-star-ratings (>=0.9,<0.10)
Requires-Dist: django-tables2 (>=2.4,<3.0)
Requires-Dist: django-taggit (>=4,<5)
Requires-Dist: django-versatileimagefield (>=2,<3)
Requires-Dist: django-watson (>=1.6,<2.0)
Requires-Dist: django3-collectionfield (>=1,<2)
Requires-Dist: djangorestframework (>=3.14,<4.0)
Requires-Dist: drf-generators (>=0.5,<0.6)
Requires-Dist: drf-multiple-serializer (>=0.2,<0.3)
Requires-Dist: numpy (>=1.23,<2.0)
Requires-Dist: platformdirs (>=2.5,<3.0)
Requires-Dist: psycopg2 (>=2,<3) ; extra == "pgsql"
Requires-Dist: pytz
Requires-Dist: pyyaml (>=6,<7)
Requires-Dist: uWSGI (>=2,<3)
Requires-Dist: uritemplate (>=4,<5)
Project-URL: Repository, https://github.com/camerahub/camerahub
